setup.cfg
setup.py
ezalchemy/__init__.py
ezalchemy/constants.py
ezalchemy/ezalchemy.py
ezalchemy.egg-info/PKG-INFO
ezalchemy.egg-info/SOURCES.txt
ezalchemy.egg-info/dependency_links.txt
ezalchemy.egg-info/requires.txt
ezalchemy.egg-info/top_level.txt