Metadata-Version: 1.1
Name: ezalchemy
Version: 1.1.2
Summary: Thin wrapper around sqlalchemy for quick database integration
Home-page: https://github.com/mathiasbc/EZAlchemy
Author: Mathias Bustamante
Author-email: mathiasbc@gmail.com
License: UNKNOWN
Download-URL: https://github.com/mathiasbc/EZAlchemy/tarball/1.1.2
Platform: UNKNOWN
